{
  "extraction_date": "2025-07-14T10:14:53.747402",
  "method": "Three_Strategies_V2_Isolated",
  "statistics": {
    "PageText": {
      "total_files": 10,
      "files_with_data": 10,
      "pages_with_data": 249,
      "diretoria_especial_docs": 23,
      "extracted_successfully": 23,
      "field_extraction_counts": {
        "processo": 23,
        "numero_autos": 23,
        "juizo": 23,
        "comarca": 23,
        "perito_nome": 23,
        "cpf_perito": 23,
        "especialidade": 23,
        "valor_arbitrado": 23,
        "autor": 23,
        "parte_contraria": 23,
        "destino": 23
      },
      "multi_page_docs": 12,
      "inferred_values": 0,
      "multi_page_searches": 23,
      "perito_by_cpf": 0,
      "validation_failures": {
        "processo": 0,
        "numero_autos": 0,
        "juizo": 0,
        "comarca": 0,
        "perito_nome": 0,
        "cpf_perito": 0,
        "especialidade": 0,
        "valor_arbitrado": 0,
        "autor": 0,
        "parte_contraria": 0,
        "destino": 0
      }
    },
    "AdvancedLayout": {
      "total_files": 10,
      "files_with_data": 10,
      "pages_with_data": 249,
      "diretoria_especial_docs": 23,
      "extracted_successfully": 23,
      "field_extraction_counts": {
        "processo": 23,
        "numero_autos": 23,
        "juizo": 23,
        "comarca": 23,
        "perito_nome": 23,
        "cpf_perito": 23,
        "especialidade": 23,
        "valor_arbitrado": 23,
        "autor": 23,
        "parte_contraria": 23,
        "destino": 23
      },
      "multi_page_docs": 12,
      "inferred_values": 0,
      "multi_page_searches": 23,
      "perito_by_cpf": 0,
      "validation_failures": {
        "processo": 0,
        "numero_autos": 0,
        "juizo": 0,
        "comarca": 0,
        "perito_nome": 0,
        "cpf_perito": 0,
        "especialidade": 0,
        "valor_arbitrado": 0,
        "autor": 0,
        "parte_contraria": 0,
        "destino": 0
      }
    },
    "LayoutPreserving": {
      "total_files": 10,
      "files_with_data": 10,
      "pages_with_data": 249,
      "diretoria_especial_docs": 23,
      "extracted_successfully": 23,
      "field_extraction_counts": {
        "processo": 23,
        "numero_autos": 23,
        "juizo": 23,
        "comarca": 23,
        "perito_nome": 23,
        "cpf_perito": 23,
        "especialidade": 23,
        "valor_arbitrado": 23,
        "autor": 23,
        "parte_contraria": 23,
        "destino": 23
      },
      "multi_page_docs": 12,
      "inferred_values": 0,
      "multi_page_searches": 23,
      "perito_by_cpf": 0,
      "validation_failures": {
        "processo": 0,
        "numero_autos": 0,
        "juizo": 0,
        "comarca": 0,
        "perito_nome": 0,
        "cpf_perito": 0,
        "especialidade": 0,
        "valor_arbitrado": 0,
        "autor": 0,
        "parte_contraria": 0,
        "destino": 0
      }
    }
  },
  "results_by_strategy": {
    "PageText": [
      {
        "processo": "000025-10.2024.8.15",
        "numero_autos": "0800556-88.2018.8.15.0601",
        "juizo": "Vara Única",
        "comarca": "Belém Interessado",
        "perito_nome": "Felipe Queiroga Gadelha",
        "cpf_perito": "021.205.144-02",
        "especialidade": "Grafotécnico",
        "valor_arbitrado": "350.00",
        "autor": "Juízo da Vara Única da Comarca de Belém",
        "parte_contraria": "o sighop felipe queiroga gadelha (0000172)         SEI 000025-10.2024.8.15 / pg. 34 TRIBUNAL DE JUSTIÇA DA PARAÍBA",
        "destino": "Programação Orçamentária deste Tribunal",
        "source_file": "000025102024815._cache.json",
        "start_page": 35,
        "end_page": 35,
        "page_count": 1,
        "extraction_strategy": "PageText"
      },
      {
        "processo": "000025-10.2024.8.15",
        "numero_autos": "0800556-88.2018.8.15.0601",
        "juizo": "Vara Única",
        "comarca": "Belém Interessado",
        "perito_nome": "Felipe Queiroga Gadelha",
        "cpf_perito": "021.205.144-02",
        "especialidade": "Grafotécnico",
        "valor_arbitrado": "350.00",
        "autor": "Juízo da Vara Única da Comarca de Belém",
        "parte_contraria": "ados na tabela constante no Anexo da Resolução 232",
        "destino": "Programação Orçamentária deste Tribunal",
        "source_file": "000025102024815._cache.json",
        "start_page": 36,
        "end_page": 38,
        "page_count": 3,
        "extraction_strategy": "PageText"
      },
      {
        "processo": "000025-10.2024.8.15",
        "numero_autos": "0800556-88.2018.8.15.0601",
        "juizo": "Vara Única",
        "comarca": "Belém Interessado",
        "perito_nome": "Felipe Queiroga Gadelha",
        "cpf_perito": "021.205.144-02",
        "especialidade": "Grafotécnico",
        "valor_arbitrado": "350.00",
        "autor": "Juízo da Vara Única da Comarca de Belém",
        "parte_contraria": "o sighop felipe queiroga gadelha (0000172)         SEI 000025-10.2024.8.15 / pg. 34 TRIBUNAL DE JUSTIÇA DA PARAÍBA",
        "destino": "Programação Orçamentária deste Tribunal",
        "source_file": "000025102024815_cache.json",
        "start_page": 35,
        "end_page": 35,
        "page_count": 1,
        "extraction_strategy": "PageText"
      },
      {
        "processo": "000025-10.2024.8.15",
        "numero_autos": "0800556-88.2018.8.15.0601",
        "juizo": "Vara Única",
        "comarca": "Belém Interessado",
        "perito_nome": "Felipe Queiroga Gadelha",
        "cpf_perito": "021.205.144-02",
        "especialidade": "Grafotécnico",
        "valor_arbitrado": "350.00",
        "autor": "Juízo da Vara Única da Comarca de Belém",
        "parte_contraria": "ados na tabela constante no Anexo da Resolução 232",
        "destino": "Programação Orçamentária deste Tribunal",
        "source_file": "000025102024815_cache.json",
        "start_page": 36,
        "end_page": 38,
        "page_count": 3,
        "extraction_strategy": "PageText"
      },
      {
        "processo": "000183-70.2024.8.15",
        "numero_autos": "0808633-24.2023.8.15.0371",
        "juizo": "5ª VARA MISTA DE SOUSA",
        "comarca": "Sousa",
        "perito_nome": "FELIPE QUEIROGA GADELHA",
        "cpf_perito": "021.205.144-02",
        "especialidade": "Grafotécnico",
        "valor_arbitrado": "256.04",
        "autor": "izado pelo inciso IV",
        "parte_contraria": "BANCO BRADESCO",
        "destino": "Programação Orçamentária",
        "source_file": "0001210_cache.json",
        "start_page": 1,
        "end_page": 1,
        "page_count": 1,
        "extraction_strategy": "PageText"
      },
      {
        "processo": "000183-70.2024.8.15",
        "numero_autos": "0808633-24.2023.8.15.0371",
        "juizo": "5ª VARA MISTA DE SOUSA",
        "comarca": "Sousa",
        "perito_nome": "FELIPE QUEIROGA GADELHA",
        "cpf_perito": "021.205.144-02",
        "especialidade": "Grafotécnico",
        "valor_arbitrado": "256.04",
        "autor": "izado pelo inciso IV",
        "parte_contraria": "BANCO BRADESCO",
        "destino": "Programação Orçamentária",
        "source_file": "0001210_cache.json",
        "start_page": 2,
        "end_page": 3,
        "page_count": 2,
        "extraction_strategy": "PageText"
      },
      {
        "processo": "000121-44.2024.8.15",
        "numero_autos": "0800492-65.2017.8.15.0261",
        "juizo": "2ª Vara Mista",
        "comarca": "Piancó Interessado",
        "perito_nome": "Felipe Queiroga Gadelha",
        "cpf_perito": "021.205.144-02",
        "especialidade": "Felipe Queiroga Gadelha",
        "valor_arbitrado": "700.00",
        "autor": "IAGO",
        "parte_contraria": "COSTA E PAULINO LTDA (NOME",
        "destino": "Fórum",
        "source_file": "000121442024815_cache.json",
        "start_page": 5,
        "end_page": 23,
        "page_count": 19,
        "extraction_strategy": "PageText"
      },
      {
        "processo": "000121-44.2024.8.15",
        "numero_autos": "0800492-65.2017.8.15.0261",
        "juizo": "2ª Vara Mista",
        "comarca": "Piancó Interessado",
        "perito_nome": "Felipe Queiroga Gadelha",
        "cpf_perito": "021.205.144-02",
        "especialidade": "Felipe Queiroga Gadelha",
        "valor_arbitrado": "700.00",
        "autor": "IAGO",
        "parte_contraria": "COSTA E PAULINO LTDA (NOME",
        "destino": "Conselho da Magistratura",
        "source_file": "000121442024815_cache.json",
        "start_page": 24,
        "end_page": 24,
        "page_count": 1,
        "extraction_strategy": "PageText"
      },
      {
        "processo": "000121-44.2024.8.15",
        "numero_autos": "0800492-65.2017.8.15.0261",
        "juizo": "2ª Vara Mista",
        "comarca": "Piancó Interessado",
        "perito_nome": "Felipe Queiroga Gadelha",
        "cpf_perito": "021.205.144-02",
        "especialidade": "Felipe Queiroga Gadelha",
        "valor_arbitrado": "700.00",
        "autor": "IAGO MINERVINO DE CARVALHO",
        "parte_contraria": "COSTA E PAULINO LTDA (NOME",
        "destino": "Conselho da Magistratura",
        "source_file": "000121442024815_cache.json",
        "start_page": 25,
        "end_page": 40,
        "page_count": 16,
        "extraction_strategy": "PageText"
      },
      {
        "processo": "000183-70.2024.8.15",
        "numero_autos": "0808633-24.2023.8.15.0371",
        "juizo": "5ª VARA MISTA DE SOUSA",
        "comarca": "Sousa",
        "perito_nome": "FELIPE QUEIROGA GADELHA",
        "cpf_perito": "021.205.144-02",
        "especialidade": "Grafotécnico",
        "valor_arbitrado": "256.04",
        "autor": "izado pelo inciso IV",
        "parte_contraria": "BANCO BRADESCO",
        "destino": "Programação Orçamentária",
        "source_file": "000183702024815_cache.json",
        "start_page": 11,
        "end_page": 11,
        "page_count": 1,
        "extraction_strategy": "PageText"
      },
      {
        "processo": "000183-70.2024.8.15",
        "numero_autos": "0808633-24.2023.8.15.0371",
        "juizo": "5ª VARA MISTA DE SOUSA",
        "comarca": "Sousa",
        "perito_nome": "FELIPE QUEIROGA GADELHA",
        "cpf_perito": "021.205.144-02",
        "especialidade": "Grafotécnico",
        "valor_arbitrado": "256.04",
        "autor": "izado pelo inciso IV",
        "parte_contraria": "BANCO BRADESCO",
        "destino": "Programação Orçamentária",
        "source_file": "000183702024815_cache.json",
        "start_page": 12,
        "end_page": 16,
        "page_count": 5,
        "extraction_strategy": "PageText"
      },
      {
        "processo": "000206-64.2024.8.15",
        "numero_autos": "0808972-80.2023.8.15.0371",
        "juizo": "3ª Vara",
        "comarca": "Sousa Interessado",
        "perito_nome": "Médico Psiquiatra",
        "cpf_perito": "046.443.074-75",
        "especialidade": "Médico Psiquiatra",
        "valor_arbitrado": "370.00",
        "autor": "izado pelo inciso IV",
        "parte_contraria": "GERALDO VICENTE FILHO",
        "destino": "Programação Orçamentária",
        "source_file": "0002066420248151_cache.json",
        "start_page": 17,
        "end_page": 17,
        "page_count": 1,
        "extraction_strategy": "PageText"
      },
      {
        "processo": "000206-64.2024.8.15",
        "numero_autos": "0808972-80.2023.8.15.0371",
        "juizo": "3ª Vara",
        "comarca": "Sousa Interessado",
        "perito_nome": "Médico Psiquiatra",
        "cpf_perito": "046.443.074-75",
        "especialidade": "Médico Psiquiatra",
        "valor_arbitrado": "370.00",
        "autor": "izado pelo inciso IV",
        "parte_contraria": "GERALDO VICENTE FILHO",
        "destino": "Programação Orçamentária",
        "source_file": "0002066420248151_cache.json",
        "start_page": 18,
        "end_page": 27,
        "page_count": 10,
        "extraction_strategy": "PageText"
      },
      {
        "processo": "000206-64.2024.8.15",
        "numero_autos": "0808972-80.2023.8.15.0371",
        "juizo": "3ª Vara",
        "comarca": "Sousa Interessado",
        "perito_nome": "OS ESCLARECIMENTOS ADICIONAIS QUE REPUTE",
        "cpf_perito": "046.443.074-75",
        "especialidade": "Médico Psiquiatra",
        "valor_arbitrado": "370.00",
        "autor": "izo a despesa",
        "parte_contraria": "GERALDO VICENTE FILHO",
        "destino": "Programação Orçamentária deste Tribunal",
        "source_file": "0002066420248151_cache.json",
        "start_page": 28,
        "end_page": 28,
        "page_count": 1,
        "extraction_strategy": "PageText"
      },
      {
        "processo": "000206-64.2024.8.15",
        "numero_autos": "0808972-80.2023.8.15.0371",
        "juizo": "3ª Vara",
        "comarca": "Sousa Interessado",
        "perito_nome": "Médico Psiquiatra",
        "cpf_perito": "046.443.074-75",
        "especialidade": "Médico Psiquiatra",
        "valor_arbitrado": "370.00",
        "autor": "izo a despesa",
        "parte_contraria": "GERALDO VICENTE FILHO",
        "destino": "Programação Orçamentária deste Tribunal",
        "source_file": "0002066420248151_cache.json",
        "start_page": 29,
        "end_page": 30,
        "page_count": 2,
        "extraction_strategy": "PageText"
      },
      {
        "processo": "000206-64.2024.8.15",
        "numero_autos": "0808972-80.2023.8.15.0371",
        "juizo": "3ª Vara",
        "comarca": "Sousa Interessado",
        "perito_nome": "Médico Psiquiatra",
        "cpf_perito": "046.443.074-75",
        "especialidade": "Médico Psiquiatra",
        "valor_arbitrado": "370.00",
        "autor": "izado pelo inciso IV",
        "parte_contraria": "GERALDO VICENTE FILHO",
        "destino": "Programação Orçamentária",
        "source_file": "0002066420248152_cache.json",
        "start_page": 17,
        "end_page": 17,
        "page_count": 1,
        "extraction_strategy": "PageText"
      },
      {
        "processo": "000206-64.2024.8.15",
        "numero_autos": "0808972-80.2023.8.15.0371",
        "juizo": "3ª Vara",
        "comarca": "Sousa Interessado",
        "perito_nome": "Médico Psiquiatra",
        "cpf_perito": "046.443.074-75",
        "especialidade": "Médico Psiquiatra",
        "valor_arbitrado": "370.00",
        "autor": "izado pelo inciso IV",
        "parte_contraria": "GERALDO VICENTE FILHO",
        "destino": "Programação Orçamentária",
        "source_file": "0002066420248152_cache.json",
        "start_page": 18,
        "end_page": 27,
        "page_count": 10,
        "extraction_strategy": "PageText"
      },
      {
        "processo": "000206-64.2024.8.15",
        "numero_autos": "0808972-80.2023.8.15.0371",
        "juizo": "3ª Vara",
        "comarca": "Sousa Interessado",
        "perito_nome": "OS ESCLARECIMENTOS ADICIONAIS QUE REPUTE",
        "cpf_perito": "046.443.074-75",
        "especialidade": "Médico Psiquiatra",
        "valor_arbitrado": "370.00",
        "autor": "izo a despesa",
        "parte_contraria": "GERALDO VICENTE FILHO",
        "destino": "Programação Orçamentária deste Tribunal",
        "source_file": "0002066420248152_cache.json",
        "start_page": 28,
        "end_page": 28,
        "page_count": 1,
        "extraction_strategy": "PageText"
      },
      {
        "processo": "000206-64.2024.8.15",
        "numero_autos": "0808972-80.2023.8.15.0371",
        "juizo": "3ª Vara",
        "comarca": "Sousa Interessado",
        "perito_nome": "Médico Psiquiatra",
        "cpf_perito": "046.443.074-75",
        "especialidade": "Médico Psiquiatra",
        "valor_arbitrado": "370.00",
        "autor": "izo a despesa",
        "parte_contraria": "GERALDO VICENTE FILHO",
        "destino": "Programação Orçamentária deste Tribunal",
        "source_file": "0002066420248152_cache.json",
        "start_page": 29,
        "end_page": 30,
        "page_count": 2,
        "extraction_strategy": "PageText"
      },
      {
        "processo": "000206-64.2024.8.15",
        "numero_autos": "0808972-80.2023.8.15.0371",
        "juizo": "3ª Vara",
        "comarca": "Sousa Interessado",
        "perito_nome": "Médico Psiquiatra",
        "cpf_perito": "046.443.074-75",
        "especialidade": "Médico Psiquiatra",
        "valor_arbitrado": "370.00",
        "autor": "izado pelo inciso IV",
        "parte_contraria": "GERALDO VICENTE FILHO",
        "destino": "Programação Orçamentária",
        "source_file": "000206642024815_cache.json",
        "start_page": 17,
        "end_page": 17,
        "page_count": 1,
        "extraction_strategy": "PageText"
      },
      {
        "processo": "000206-64.2024.8.15",
        "numero_autos": "0808972-80.2023.8.15.0371",
        "juizo": "3ª Vara",
        "comarca": "Sousa Interessado",
        "perito_nome": "Médico Psiquiatra",
        "cpf_perito": "046.443.074-75",
        "especialidade": "Médico Psiquiatra",
        "valor_arbitrado": "370.00",
        "autor": "izado pelo inciso IV",
        "parte_contraria": "GERALDO VICENTE FILHO",
        "destino": "Programação Orçamentária",
        "source_file": "000206642024815_cache.json",
        "start_page": 18,
        "end_page": 22,
        "page_count": 5,
        "extraction_strategy": "PageText"
      },
      {
        "processo": "000356-08.2024.8.15",
        "numero_autos": "2305150-95.1330.5.70.0000",
        "juizo": "DIREITO DA VARA",
        "comarca": "SOUSA",
        "perito_nome": "Felipe Queiroga Gadelha",
        "cpf_perito": "047.122.374-30",
        "especialidade": "Grafocopista Felipe Queiroga Gadelha",
        "valor_arbitrado": "398.81",
        "autor": "pugna pela concessão",
        "parte_contraria": "BANCO\nSANTANDER BRASIL S.A",
        "destino": "Programação Orçamentária deste Tribunal",
        "source_file": "0003560820248151_cache.json",
        "start_page": 24,
        "end_page": 24,
        "page_count": 1,
        "extraction_strategy": "PageText"
      },
      {
        "processo": "000356-08.2024.8.15",
        "numero_autos": "0803338-06.2023.8.15.0371",
        "juizo": "5ª Vara Mista",
        "comarca": "Sousa Interessado",
        "perito_nome": "Felipe Queiroga Gadelha",
        "cpf_perito": "021.205.144-02",
        "especialidade": "Grafocopista Felipe Queiroga Gadelha",
        "valor_arbitrado": "398.81",
        "autor": "izo a despesa",
        "parte_contraria": "BANCO\nSANTANDER BRASIL S.A",
        "destino": "Programação Orçamentária deste Tribunal",
        "source_file": "0003560820248151_cache.json",
        "start_page": 25,
        "end_page": 30,
        "page_count": 6,
        "extraction_strategy": "PageText"
      }
    ],
    "AdvancedLayout": [
      {
        "processo": "000025-10.2024.8.15",
        "numero_autos": "0800556-88.2018.8.15.0601",
        "juizo": "Vara Única",
        "comarca": "Belém Interessado",
        "perito_nome": "Felipe Queiroga Gadelha",
        "cpf_perito": "021.205.144-02",
        "especialidade": "Grafotécnico",
        "valor_arbitrado": "350.00",
        "autor": "Juízo da Vara Única da Comarca de Belém",
        "parte_contraria": "o sighop felipe queiroga gadelha (0000172)         SEI 000025-10.2024.8.15 / pg. 34                                                                                  TRIBUNAL DE JUSTIÇA DA PARAÍBA",
        "destino": "Programação  Orçamentária  deste  Tribunal",
        "source_file": "000025102024815._cache.json",
        "start_page": 35,
        "end_page": 35,
        "page_count": 1,
        "extraction_strategy": "AdvancedLayout"
      },
      {
        "processo": "000025-10.2024.8.15",
        "numero_autos": "0800556-88.2018.8.15.0601",
        "juizo": "Vara Única",
        "comarca": "Belém Interessado",
        "perito_nome": "Felipe Queiroga Gadelha",
        "cpf_perito": "021.205.144-02",
        "especialidade": "Grafotécnico",
        "valor_arbitrado": "350.00",
        "autor": "Juízo da Vara Única da Comarca de Belém",
        "parte_contraria": "ados na tabela constante no Anexo da Resolução 232",
        "destino": "Programação  Orçamentária  deste  Tribunal",
        "source_file": "000025102024815._cache.json",
        "start_page": 36,
        "end_page": 38,
        "page_count": 3,
        "extraction_strategy": "AdvancedLayout"
      },
      {
        "processo": "000025-10.2024.8.15",
        "numero_autos": "0800556-88.2018.8.15.0601",
        "juizo": "Vara Única",
        "comarca": "Belém Interessado",
        "perito_nome": "Felipe Queiroga Gadelha",
        "cpf_perito": "021.205.144-02",
        "especialidade": "Grafotécnico",
        "valor_arbitrado": "350.00",
        "autor": "Juízo da Vara Única da Comarca de Belém",
        "parte_contraria": "o sighop felipe queiroga gadelha (0000172)         SEI 000025-10.2024.8.15 / pg. 34                                                                                  TRIBUNAL DE JUSTIÇA DA PARAÍBA",
        "destino": "Programação  Orçamentária  deste  Tribunal",
        "source_file": "000025102024815_cache.json",
        "start_page": 35,
        "end_page": 35,
        "page_count": 1,
        "extraction_strategy": "AdvancedLayout"
      },
      {
        "processo": "000025-10.2024.8.15",
        "numero_autos": "0800556-88.2018.8.15.0601",
        "juizo": "Vara Única",
        "comarca": "Belém Interessado",
        "perito_nome": "Felipe Queiroga Gadelha",
        "cpf_perito": "021.205.144-02",
        "especialidade": "Grafotécnico",
        "valor_arbitrado": "350.00",
        "autor": "Juízo da Vara Única da Comarca de Belém",
        "parte_contraria": "ados na tabela constante no Anexo da Resolução 232",
        "destino": "Programação  Orçamentária  deste  Tribunal",
        "source_file": "000025102024815_cache.json",
        "start_page": 36,
        "end_page": 38,
        "page_count": 3,
        "extraction_strategy": "AdvancedLayout"
      },
      {
        "processo": "000183-70.2024.8.15",
        "numero_autos": "0808633-24.2023.8.15.0371",
        "juizo": "5ª VARA MISTA DE SOUSA",
        "comarca": "Sousa",
        "perito_nome": "FELIPE QUEIROGA GADELHA",
        "cpf_perito": "021.205.144-02",
        "especialidade": "Grafotécnico",
        "valor_arbitrado": "256.04",
        "autor": "izado pelo inciso IV",
        "parte_contraria": "BANCO BRADESCO",
        "destino": "Programação Orçamentária",
        "source_file": "0001210_cache.json",
        "start_page": 1,
        "end_page": 1,
        "page_count": 1,
        "extraction_strategy": "AdvancedLayout"
      },
      {
        "processo": "000183-70.2024.8.15",
        "numero_autos": "0808633-24.2023.8.15.0371",
        "juizo": "5ª VARA MISTA DE SOUSA",
        "comarca": "Sousa",
        "perito_nome": "FELIPE QUEIROGA GADELHA",
        "cpf_perito": "021.205.144-02",
        "especialidade": "Grafotécnico",
        "valor_arbitrado": "256.04",
        "autor": "izado pelo inciso IV",
        "parte_contraria": "BANCO BRADESCO",
        "destino": "Programação Orçamentária",
        "source_file": "0001210_cache.json",
        "start_page": 2,
        "end_page": 3,
        "page_count": 2,
        "extraction_strategy": "AdvancedLayout"
      },
      {
        "processo": "000121-44.2024.8.15",
        "numero_autos": "0800492-65.2017.8.15.0261",
        "juizo": "2ª Vara Mista",
        "comarca": "Piancó Interessado",
        "perito_nome": "Felipe Queiroga Gadelha",
        "cpf_perito": "021.205.144-02",
        "especialidade": "Felipe Queiroga Gadelha",
        "valor_arbitrado": "700.00",
        "autor": "IAGO",
        "parte_contraria": "COSTA E PAULINO LTDA (NOME",
        "destino": "Fórum",
        "source_file": "000121442024815_cache.json",
        "start_page": 5,
        "end_page": 23,
        "page_count": 19,
        "extraction_strategy": "AdvancedLayout"
      },
      {
        "processo": "000121-44.2024.8.15",
        "numero_autos": "0800492-65.2017.8.15.0261",
        "juizo": "2ª Vara Mista",
        "comarca": "Piancó Interessado",
        "perito_nome": "Felipe Queiroga Gadelha",
        "cpf_perito": "021.205.144-02",
        "especialidade": "Felipe Queiroga Gadelha",
        "valor_arbitrado": "700.00",
        "autor": "IAGO",
        "parte_contraria": "COSTA E PAULINO LTDA (NOME",
        "destino": "Conselho da Magistratura",
        "source_file": "000121442024815_cache.json",
        "start_page": 24,
        "end_page": 24,
        "page_count": 1,
        "extraction_strategy": "AdvancedLayout"
      },
      {
        "processo": "000121-44.2024.8.15",
        "numero_autos": "0800492-65.2017.8.15.0261",
        "juizo": "2ª Vara Mista",
        "comarca": "Piancó Interessado",
        "perito_nome": "Felipe Queiroga Gadelha",
        "cpf_perito": "021.205.144-02",
        "especialidade": "Felipe Queiroga Gadelha",
        "valor_arbitrado": "700.00",
        "autor": "IAGO MINERVINO DE CARVALHO",
        "parte_contraria": "COSTA E PAULINO LTDA (NOME",
        "destino": "Conselho da Magistratura",
        "source_file": "000121442024815_cache.json",
        "start_page": 25,
        "end_page": 40,
        "page_count": 16,
        "extraction_strategy": "AdvancedLayout"
      },
      {
        "processo": "000183-70.2024.8.15",
        "numero_autos": "0808633-24.2023.8.15.0371",
        "juizo": "5ª VARA MISTA DE SOUSA",
        "comarca": "Sousa",
        "perito_nome": "FELIPE QUEIROGA GADELHA",
        "cpf_perito": "021.205.144-02",
        "especialidade": "Grafotécnico",
        "valor_arbitrado": "256.04",
        "autor": "izado pelo inciso IV",
        "parte_contraria": "BANCO BRADESCO",
        "destino": "Programação Orçamentária",
        "source_file": "000183702024815_cache.json",
        "start_page": 11,
        "end_page": 11,
        "page_count": 1,
        "extraction_strategy": "AdvancedLayout"
      },
      {
        "processo": "000183-70.2024.8.15",
        "numero_autos": "0808633-24.2023.8.15.0371",
        "juizo": "5ª VARA MISTA DE SOUSA",
        "comarca": "Sousa",
        "perito_nome": "FELIPE QUEIROGA GADELHA",
        "cpf_perito": "021.205.144-02",
        "especialidade": "Grafotécnico",
        "valor_arbitrado": "256.04",
        "autor": "izado pelo inciso IV",
        "parte_contraria": "BANCO BRADESCO",
        "destino": "Programação Orçamentária",
        "source_file": "000183702024815_cache.json",
        "start_page": 12,
        "end_page": 16,
        "page_count": 5,
        "extraction_strategy": "AdvancedLayout"
      },
      {
        "processo": "000206-64.2024.8.15",
        "numero_autos": "0808972-80.2023.8.15.0371",
        "juizo": "3ª Vara",
        "comarca": "Sousa Interessado",
        "perito_nome": "Médico Psiquiatra",
        "cpf_perito": "046.443.074-75",
        "especialidade": "Médico Psiquiatra",
        "valor_arbitrado": "370.00",
        "autor": "izado pelo inciso IV",
        "parte_contraria": "GERALDO  VICENTE  FILHO",
        "destino": "Programação Orçamentária",
        "source_file": "0002066420248151_cache.json",
        "start_page": 17,
        "end_page": 17,
        "page_count": 1,
        "extraction_strategy": "AdvancedLayout"
      },
      {
        "processo": "000206-64.2024.8.15",
        "numero_autos": "0808972-80.2023.8.15.0371",
        "juizo": "3ª Vara",
        "comarca": "Sousa Interessado",
        "perito_nome": "Médico Psiquiatra",
        "cpf_perito": "046.443.074-75",
        "especialidade": "Médico Psiquiatra",
        "valor_arbitrado": "370.00",
        "autor": "izado pelo inciso IV",
        "parte_contraria": "GERALDO  VICENTE  FILHO",
        "destino": "Programação Orçamentária",
        "source_file": "0002066420248151_cache.json",
        "start_page": 18,
        "end_page": 27,
        "page_count": 10,
        "extraction_strategy": "AdvancedLayout"
      },
      {
        "processo": "000206-64.2024.8.15",
        "numero_autos": "0808972-80.2023.8.15.0371",
        "juizo": "3ª Vara",
        "comarca": "Sousa Interessado",
        "perito_nome": "OS ESCLARECIMENTOS ADICIONAIS QUE REPUTE",
        "cpf_perito": "046.443.074-75",
        "especialidade": "Médico Psiquiatra",
        "valor_arbitrado": "370.00",
        "autor": "izo a despesa",
        "parte_contraria": "GERALDO VICENTE FILHO",
        "destino": "Programação Orçamentária deste Tribunal",
        "source_file": "0002066420248151_cache.json",
        "start_page": 28,
        "end_page": 28,
        "page_count": 1,
        "extraction_strategy": "AdvancedLayout"
      },
      {
        "processo": "000206-64.2024.8.15",
        "numero_autos": "0808972-80.2023.8.15.0371",
        "juizo": "3ª Vara",
        "comarca": "Sousa Interessado",
        "perito_nome": "Médico Psiquiatra",
        "cpf_perito": "046.443.074-75",
        "especialidade": "Médico Psiquiatra",
        "valor_arbitrado": "370.00",
        "autor": "izo a despesa",
        "parte_contraria": "GERALDO VICENTE FILHO",
        "destino": "Programação Orçamentária deste Tribunal",
        "source_file": "0002066420248151_cache.json",
        "start_page": 29,
        "end_page": 30,
        "page_count": 2,
        "extraction_strategy": "AdvancedLayout"
      },
      {
        "processo": "000206-64.2024.8.15",
        "numero_autos": "0808972-80.2023.8.15.0371",
        "juizo": "3ª Vara",
        "comarca": "Sousa Interessado",
        "perito_nome": "Médico Psiquiatra",
        "cpf_perito": "046.443.074-75",
        "especialidade": "Médico Psiquiatra",
        "valor_arbitrado": "370.00",
        "autor": "izado pelo inciso IV",
        "parte_contraria": "GERALDO  VICENTE  FILHO",
        "destino": "Programação Orçamentária",
        "source_file": "0002066420248152_cache.json",
        "start_page": 17,
        "end_page": 17,
        "page_count": 1,
        "extraction_strategy": "AdvancedLayout"
      },
      {
        "processo": "000206-64.2024.8.15",
        "numero_autos": "0808972-80.2023.8.15.0371",
        "juizo": "3ª Vara",
        "comarca": "Sousa Interessado",
        "perito_nome": "Médico Psiquiatra",
        "cpf_perito": "046.443.074-75",
        "especialidade": "Médico Psiquiatra",
        "valor_arbitrado": "370.00",
        "autor": "izado pelo inciso IV",
        "parte_contraria": "GERALDO  VICENTE  FILHO",
        "destino": "Programação Orçamentária",
        "source_file": "0002066420248152_cache.json",
        "start_page": 18,
        "end_page": 27,
        "page_count": 10,
        "extraction_strategy": "AdvancedLayout"
      },
      {
        "processo": "000206-64.2024.8.15",
        "numero_autos": "0808972-80.2023.8.15.0371",
        "juizo": "3ª Vara",
        "comarca": "Sousa Interessado",
        "perito_nome": "OS ESCLARECIMENTOS ADICIONAIS QUE REPUTE",
        "cpf_perito": "046.443.074-75",
        "especialidade": "Médico Psiquiatra",
        "valor_arbitrado": "370.00",
        "autor": "izo a despesa",
        "parte_contraria": "GERALDO VICENTE FILHO",
        "destino": "Programação Orçamentária deste Tribunal",
        "source_file": "0002066420248152_cache.json",
        "start_page": 28,
        "end_page": 28,
        "page_count": 1,
        "extraction_strategy": "AdvancedLayout"
      },
      {
        "processo": "000206-64.2024.8.15",
        "numero_autos": "0808972-80.2023.8.15.0371",
        "juizo": "3ª Vara",
        "comarca": "Sousa Interessado",
        "perito_nome": "Médico Psiquiatra",
        "cpf_perito": "046.443.074-75",
        "especialidade": "Médico Psiquiatra",
        "valor_arbitrado": "370.00",
        "autor": "izo a despesa",
        "parte_contraria": "GERALDO VICENTE FILHO",
        "destino": "Programação Orçamentária deste Tribunal",
        "source_file": "0002066420248152_cache.json",
        "start_page": 29,
        "end_page": 30,
        "page_count": 2,
        "extraction_strategy": "AdvancedLayout"
      },
      {
        "processo": "000206-64.2024.8.15",
        "numero_autos": "0808972-80.2023.8.15.0371",
        "juizo": "3ª Vara",
        "comarca": "Sousa Interessado",
        "perito_nome": "Médico Psiquiatra",
        "cpf_perito": "046.443.074-75",
        "especialidade": "Médico Psiquiatra",
        "valor_arbitrado": "370.00",
        "autor": "izado pelo inciso IV",
        "parte_contraria": "GERALDO  VICENTE  FILHO",
        "destino": "Programação Orçamentária",
        "source_file": "000206642024815_cache.json",
        "start_page": 17,
        "end_page": 17,
        "page_count": 1,
        "extraction_strategy": "AdvancedLayout"
      },
      {
        "processo": "000206-64.2024.8.15",
        "numero_autos": "0808972-80.2023.8.15.0371",
        "juizo": "3ª Vara",
        "comarca": "Sousa Interessado",
        "perito_nome": "Médico Psiquiatra",
        "cpf_perito": "046.443.074-75",
        "especialidade": "Médico Psiquiatra",
        "valor_arbitrado": "370.00",
        "autor": "izado pelo inciso IV",
        "parte_contraria": "GERALDO  VICENTE  FILHO",
        "destino": "Programação Orçamentária",
        "source_file": "000206642024815_cache.json",
        "start_page": 18,
        "end_page": 22,
        "page_count": 5,
        "extraction_strategy": "AdvancedLayout"
      },
      {
        "processo": "000356-08.2024.8.15",
        "numero_autos": "2305150-95.1330.5.70.0000",
        "juizo": "DIREITO DA VARA",
        "comarca": "SOUSA",
        "perito_nome": "Felipe Queiroga Gadelha",
        "cpf_perito": "047.122.374-30",
        "especialidade": "Grafocopista Felipe Queiroga Gadelha",
        "valor_arbitrado": "398.81",
        "autor": "pugna pela concessão",
        "parte_contraria": "BANCO\n\nSANTANDER BRASIL S.A",
        "destino": "Programação Orçamentária deste Tribunal",
        "source_file": "0003560820248151_cache.json",
        "start_page": 24,
        "end_page": 24,
        "page_count": 1,
        "extraction_strategy": "AdvancedLayout"
      },
      {
        "processo": "000356-08.2024.8.15",
        "numero_autos": "0803338-06.2023.8.15.0371",
        "juizo": "5ª Vara Mista",
        "comarca": "Sousa Interessado",
        "perito_nome": "Felipe Queiroga Gadelha",
        "cpf_perito": "021.205.144-02",
        "especialidade": "Grafocopista Felipe Queiroga Gadelha",
        "valor_arbitrado": "398.81",
        "autor": "izo a despesa",
        "parte_contraria": "BANCO\n\nSANTANDER BRASIL S.A",
        "destino": "Programação Orçamentária deste Tribunal",
        "source_file": "0003560820248151_cache.json",
        "start_page": 25,
        "end_page": 30,
        "page_count": 6,
        "extraction_strategy": "AdvancedLayout"
      }
    ],
    "LayoutPreserving": [
      {
        "processo": "000025-10.2024.8.15",
        "numero_autos": "0800556-88.2018.8.15.0601",
        "juizo": "Vara Única",
        "comarca": "Belém Interessado",
        "perito_nome": "Felipe Queiroga Gadelha",
        "cpf_perito": "021.205.144-02",
        "especialidade": "Grafotécnico",
        "valor_arbitrado": "350.00",
        "autor": "Juízo da Vara Única da Comarca de Belém",
        "parte_contraria": "o sighop felipe queiroga gadelha (0000172)         SEI 000025-10.2024.8.15 / pg. 34 TRIBUNAL DE JUSTIÇA DA PARAÍBA",
        "destino": "Programação  Orçamentária  deste  Tribunal",
        "source_file": "000025102024815._cache.json",
        "start_page": 35,
        "end_page": 35,
        "page_count": 1,
        "extraction_strategy": "LayoutPreserving"
      },
      {
        "processo": "000025-10.2024.8.15",
        "numero_autos": "0800556-88.2018.8.15.0601",
        "juizo": "Vara Única",
        "comarca": "Belém Interessado",
        "perito_nome": "Felipe Queiroga Gadelha",
        "cpf_perito": "021.205.144-02",
        "especialidade": "Grafotécnico",
        "valor_arbitrado": "350.00",
        "autor": "Juízo da Vara Única da Comarca de Belém",
        "parte_contraria": "ados na tabela constante no Anexo da Resolução 232",
        "destino": "Programação  Orçamentária  deste  Tribunal",
        "source_file": "000025102024815._cache.json",
        "start_page": 36,
        "end_page": 38,
        "page_count": 3,
        "extraction_strategy": "LayoutPreserving"
      },
      {
        "processo": "000025-10.2024.8.15",
        "numero_autos": "0800556-88.2018.8.15.0601",
        "juizo": "Vara Única",
        "comarca": "Belém Interessado",
        "perito_nome": "Felipe Queiroga Gadelha",
        "cpf_perito": "021.205.144-02",
        "especialidade": "Grafotécnico",
        "valor_arbitrado": "350.00",
        "autor": "Juízo da Vara Única da Comarca de Belém",
        "parte_contraria": "o sighop felipe queiroga gadelha (0000172)         SEI 000025-10.2024.8.15 / pg. 34 TRIBUNAL DE JUSTIÇA DA PARAÍBA",
        "destino": "Programação  Orçamentária  deste  Tribunal",
        "source_file": "000025102024815_cache.json",
        "start_page": 35,
        "end_page": 35,
        "page_count": 1,
        "extraction_strategy": "LayoutPreserving"
      },
      {
        "processo": "000025-10.2024.8.15",
        "numero_autos": "0800556-88.2018.8.15.0601",
        "juizo": "Vara Única",
        "comarca": "Belém Interessado",
        "perito_nome": "Felipe Queiroga Gadelha",
        "cpf_perito": "021.205.144-02",
        "especialidade": "Grafotécnico",
        "valor_arbitrado": "350.00",
        "autor": "Juízo da Vara Única da Comarca de Belém",
        "parte_contraria": "ados na tabela constante no Anexo da Resolução 232",
        "destino": "Programação  Orçamentária  deste  Tribunal",
        "source_file": "000025102024815_cache.json",
        "start_page": 36,
        "end_page": 38,
        "page_count": 3,
        "extraction_strategy": "LayoutPreserving"
      },
      {
        "processo": "000183-70.2024.8.15",
        "numero_autos": "0808633-24.2023.8.15.0371",
        "juizo": "5ª VARA MISTA DE SOUSA",
        "comarca": "Sousa",
        "perito_nome": "FELIPE QUEIROGA GADELHA",
        "cpf_perito": "021.205.144-02",
        "especialidade": "Grafotécnico",
        "valor_arbitrado": "256.04",
        "autor": "izado  pelo  inciso  IV",
        "parte_contraria": "BANCO BRADESCO",
        "destino": "Programação Orçamentária",
        "source_file": "0001210_cache.json",
        "start_page": 1,
        "end_page": 1,
        "page_count": 1,
        "extraction_strategy": "LayoutPreserving"
      },
      {
        "processo": "000183-70.2024.8.15",
        "numero_autos": "0808633-24.2023.8.15.0371",
        "juizo": "5ª VARA MISTA DE SOUSA",
        "comarca": "Sousa",
        "perito_nome": "FELIPE QUEIROGA GADELHA",
        "cpf_perito": "021.205.144-02",
        "especialidade": "Grafotécnico",
        "valor_arbitrado": "256.04",
        "autor": "izado  pelo  inciso  IV",
        "parte_contraria": "BANCO BRADESCO",
        "destino": "Programação Orçamentária",
        "source_file": "0001210_cache.json",
        "start_page": 2,
        "end_page": 3,
        "page_count": 2,
        "extraction_strategy": "LayoutPreserving"
      },
      {
        "processo": "000121-44.2024.8.15",
        "numero_autos": "0800492-65.2017.8.15.0261",
        "juizo": "2ª Vara Mista",
        "comarca": "Piancó Interessado",
        "perito_nome": "Felipe Queiroga Gadelha",
        "cpf_perito": "021.205.144-02",
        "especialidade": "Felipe Queiroga Gadelha",
        "valor_arbitrado": "700.00",
        "autor": "IAGO",
        "parte_contraria": "COSTA  E  PAULINO  LTDA  (NOME",
        "destino": "Fórum",
        "source_file": "000121442024815_cache.json",
        "start_page": 5,
        "end_page": 23,
        "page_count": 19,
        "extraction_strategy": "LayoutPreserving"
      },
      {
        "processo": "000121-44.2024.8.15",
        "numero_autos": "0800492-65.2017.8.15.0261",
        "juizo": "2ª Vara Mista",
        "comarca": "Piancó Interessado",
        "perito_nome": "Felipe Queiroga Gadelha",
        "cpf_perito": "021.205.144-02",
        "especialidade": "Felipe Queiroga Gadelha",
        "valor_arbitrado": "700.00",
        "autor": "IAGO",
        "parte_contraria": "COSTA  E  PAULINO  LTDA  (NOME",
        "destino": "Conselho da Magistratura",
        "source_file": "000121442024815_cache.json",
        "start_page": 24,
        "end_page": 24,
        "page_count": 1,
        "extraction_strategy": "LayoutPreserving"
      },
      {
        "processo": "000121-44.2024.8.15",
        "numero_autos": "0800492-65.2017.8.15.0261",
        "juizo": "2ª Vara Mista",
        "comarca": "Piancó Interessado",
        "perito_nome": "Felipe Queiroga Gadelha",
        "cpf_perito": "021.205.144-02",
        "especialidade": "Felipe Queiroga Gadelha",
        "valor_arbitrado": "700.00",
        "autor": "IAGO MINERVINO DE CARVALHO",
        "parte_contraria": "COSTA  E  PAULINO  LTDA  (NOME",
        "destino": "Conselho da Magistratura",
        "source_file": "000121442024815_cache.json",
        "start_page": 25,
        "end_page": 40,
        "page_count": 16,
        "extraction_strategy": "LayoutPreserving"
      },
      {
        "processo": "000183-70.2024.8.15",
        "numero_autos": "0808633-24.2023.8.15.0371",
        "juizo": "5ª VARA MISTA DE SOUSA",
        "comarca": "Sousa",
        "perito_nome": "FELIPE QUEIROGA GADELHA",
        "cpf_perito": "021.205.144-02",
        "especialidade": "Grafotécnico",
        "valor_arbitrado": "256.04",
        "autor": "izado  pelo  inciso  IV",
        "parte_contraria": "BANCO BRADESCO",
        "destino": "Programação Orçamentária",
        "source_file": "000183702024815_cache.json",
        "start_page": 11,
        "end_page": 11,
        "page_count": 1,
        "extraction_strategy": "LayoutPreserving"
      },
      {
        "processo": "000183-70.2024.8.15",
        "numero_autos": "0808633-24.2023.8.15.0371",
        "juizo": "5ª VARA MISTA DE SOUSA",
        "comarca": "Sousa",
        "perito_nome": "FELIPE QUEIROGA GADELHA",
        "cpf_perito": "021.205.144-02",
        "especialidade": "Grafotécnico",
        "valor_arbitrado": "256.04",
        "autor": "izado  pelo  inciso  IV",
        "parte_contraria": "BANCO BRADESCO",
        "destino": "Programação Orçamentária",
        "source_file": "000183702024815_cache.json",
        "start_page": 12,
        "end_page": 16,
        "page_count": 5,
        "extraction_strategy": "LayoutPreserving"
      },
      {
        "processo": "000206-64.2024.8.15",
        "numero_autos": "0808972-80.2023.8.15.0371",
        "juizo": "3ª Vara",
        "comarca": "Sousa Interessado",
        "perito_nome": "Médico Psiquiatra",
        "cpf_perito": "046.443.074-75",
        "especialidade": "Médico Psiquiatra",
        "valor_arbitrado": "370.00",
        "autor": "izado  pelo  inciso  IV",
        "parte_contraria": "GERALDO  VICENTE  FILHO",
        "destino": "Programação Orçamentária",
        "source_file": "0002066420248151_cache.json",
        "start_page": 17,
        "end_page": 17,
        "page_count": 1,
        "extraction_strategy": "LayoutPreserving"
      },
      {
        "processo": "000206-64.2024.8.15",
        "numero_autos": "0808972-80.2023.8.15.0371",
        "juizo": "3ª Vara",
        "comarca": "Sousa Interessado",
        "perito_nome": "Médico Psiquiatra",
        "cpf_perito": "046.443.074-75",
        "especialidade": "Médico Psiquiatra",
        "valor_arbitrado": "370.00",
        "autor": "izado  pelo  inciso  IV",
        "parte_contraria": "GERALDO  VICENTE  FILHO",
        "destino": "Programação Orçamentária",
        "source_file": "0002066420248151_cache.json",
        "start_page": 18,
        "end_page": 27,
        "page_count": 10,
        "extraction_strategy": "LayoutPreserving"
      },
      {
        "processo": "000206-64.2024.8.15",
        "numero_autos": "0808972-80.2023.8.15.0371",
        "juizo": "3ª Vara",
        "comarca": "Sousa Interessado",
        "perito_nome": "OS ESCLARECIMENTOS ADICIONAIS QUE REPUTE",
        "cpf_perito": "046.443.074-75",
        "especialidade": "Médico Psiquiatra",
        "valor_arbitrado": "370.00",
        "autor": "izo  a  despesa",
        "parte_contraria": "GERALDO  VICENTE  FILHO",
        "destino": "Programação Orçamentária deste Tribunal",
        "source_file": "0002066420248151_cache.json",
        "start_page": 28,
        "end_page": 28,
        "page_count": 1,
        "extraction_strategy": "LayoutPreserving"
      },
      {
        "processo": "000206-64.2024.8.15",
        "numero_autos": "0808972-80.2023.8.15.0371",
        "juizo": "3ª Vara",
        "comarca": "Sousa Interessado",
        "perito_nome": "Médico Psiquiatra",
        "cpf_perito": "046.443.074-75",
        "especialidade": "Médico Psiquiatra",
        "valor_arbitrado": "370.00",
        "autor": "izo  a  despesa",
        "parte_contraria": "GERALDO  VICENTE  FILHO",
        "destino": "Programação Orçamentária deste Tribunal",
        "source_file": "0002066420248151_cache.json",
        "start_page": 29,
        "end_page": 30,
        "page_count": 2,
        "extraction_strategy": "LayoutPreserving"
      },
      {
        "processo": "000206-64.2024.8.15",
        "numero_autos": "0808972-80.2023.8.15.0371",
        "juizo": "3ª Vara",
        "comarca": "Sousa Interessado",
        "perito_nome": "Médico Psiquiatra",
        "cpf_perito": "046.443.074-75",
        "especialidade": "Médico Psiquiatra",
        "valor_arbitrado": "370.00",
        "autor": "izado  pelo  inciso  IV",
        "parte_contraria": "GERALDO  VICENTE  FILHO",
        "destino": "Programação Orçamentária",
        "source_file": "0002066420248152_cache.json",
        "start_page": 17,
        "end_page": 17,
        "page_count": 1,
        "extraction_strategy": "LayoutPreserving"
      },
      {
        "processo": "000206-64.2024.8.15",
        "numero_autos": "0808972-80.2023.8.15.0371",
        "juizo": "3ª Vara",
        "comarca": "Sousa Interessado",
        "perito_nome": "Médico Psiquiatra",
        "cpf_perito": "046.443.074-75",
        "especialidade": "Médico Psiquiatra",
        "valor_arbitrado": "370.00",
        "autor": "izado  pelo  inciso  IV",
        "parte_contraria": "GERALDO  VICENTE  FILHO",
        "destino": "Programação Orçamentária",
        "source_file": "0002066420248152_cache.json",
        "start_page": 18,
        "end_page": 27,
        "page_count": 10,
        "extraction_strategy": "LayoutPreserving"
      },
      {
        "processo": "000206-64.2024.8.15",
        "numero_autos": "0808972-80.2023.8.15.0371",
        "juizo": "3ª Vara",
        "comarca": "Sousa Interessado",
        "perito_nome": "OS ESCLARECIMENTOS ADICIONAIS QUE REPUTE",
        "cpf_perito": "046.443.074-75",
        "especialidade": "Médico Psiquiatra",
        "valor_arbitrado": "370.00",
        "autor": "izo  a  despesa",
        "parte_contraria": "GERALDO  VICENTE  FILHO",
        "destino": "Programação Orçamentária deste Tribunal",
        "source_file": "0002066420248152_cache.json",
        "start_page": 28,
        "end_page": 28,
        "page_count": 1,
        "extraction_strategy": "LayoutPreserving"
      },
      {
        "processo": "000206-64.2024.8.15",
        "numero_autos": "0808972-80.2023.8.15.0371",
        "juizo": "3ª Vara",
        "comarca": "Sousa Interessado",
        "perito_nome": "Médico Psiquiatra",
        "cpf_perito": "046.443.074-75",
        "especialidade": "Médico Psiquiatra",
        "valor_arbitrado": "370.00",
        "autor": "izo  a  despesa",
        "parte_contraria": "GERALDO  VICENTE  FILHO",
        "destino": "Programação Orçamentária deste Tribunal",
        "source_file": "0002066420248152_cache.json",
        "start_page": 29,
        "end_page": 30,
        "page_count": 2,
        "extraction_strategy": "LayoutPreserving"
      },
      {
        "processo": "000206-64.2024.8.15",
        "numero_autos": "0808972-80.2023.8.15.0371",
        "juizo": "3ª Vara",
        "comarca": "Sousa Interessado",
        "perito_nome": "Médico Psiquiatra",
        "cpf_perito": "046.443.074-75",
        "especialidade": "Médico Psiquiatra",
        "valor_arbitrado": "370.00",
        "autor": "izado  pelo  inciso  IV",
        "parte_contraria": "GERALDO  VICENTE  FILHO",
        "destino": "Programação Orçamentária",
        "source_file": "000206642024815_cache.json",
        "start_page": 17,
        "end_page": 17,
        "page_count": 1,
        "extraction_strategy": "LayoutPreserving"
      },
      {
        "processo": "000206-64.2024.8.15",
        "numero_autos": "0808972-80.2023.8.15.0371",
        "juizo": "3ª Vara",
        "comarca": "Sousa Interessado",
        "perito_nome": "Médico Psiquiatra",
        "cpf_perito": "046.443.074-75",
        "especialidade": "Médico Psiquiatra",
        "valor_arbitrado": "370.00",
        "autor": "izado  pelo  inciso  IV",
        "parte_contraria": "GERALDO  VICENTE  FILHO",
        "destino": "Programação Orçamentária",
        "source_file": "000206642024815_cache.json",
        "start_page": 18,
        "end_page": 22,
        "page_count": 5,
        "extraction_strategy": "LayoutPreserving"
      },
      {
        "processo": "000356-08.2024.8.15",
        "numero_autos": "2305150-95.1330.5.70.0000",
        "juizo": "DIREITO DA VARA",
        "comarca": "SOUSA",
        "perito_nome": "Felipe Queiroga Gadelha",
        "cpf_perito": "047.122.374-30",
        "especialidade": "Grafocopista Felipe Queiroga Gadelha",
        "valor_arbitrado": "398.81",
        "autor": "pugna pela concessão",
        "parte_contraria": "BANCO\n\nSANTANDER BRASIL S.A",
        "destino": "Programação Orçamentária deste Tribunal",
        "source_file": "0003560820248151_cache.json",
        "start_page": 24,
        "end_page": 24,
        "page_count": 1,
        "extraction_strategy": "LayoutPreserving"
      },
      {
        "processo": "000356-08.2024.8.15",
        "numero_autos": "0803338-06.2023.8.15.0371",
        "juizo": "5ª Vara Mista",
        "comarca": "Sousa Interessado",
        "perito_nome": "Felipe Queiroga Gadelha",
        "cpf_perito": "021.205.144-02",
        "especialidade": "Grafocopista Felipe Queiroga Gadelha",
        "valor_arbitrado": "398.81",
        "autor": "izo a despesa",
        "parte_contraria": "BANCO\n\nSANTANDER BRASIL S.A",
        "destino": "Programação Orçamentária deste Tribunal",
        "source_file": "0003560820248151_cache.json",
        "start_page": 25,
        "end_page": 30,
        "page_count": 6,
        "extraction_strategy": "LayoutPreserving"
      }
    ]
  }
}